piiscan/__init__.py
piiscan/recognizer.py
piiscan-0.1.7.dist-info/LICENSE
piiscan-0.1.7.dist-info/METADATA
piiscan-0.1.7.dist-info/WHEEL
piiscan-0.1.7.dist-info/RECORD
