Metadata-Version: 2.1
Name: piiscan
Version: 0.1.7
Summary: Easy, lightweight PII scanning for network requests and logs—powered by Microsoft Presidio and en_spacy_pii_fast
Author: Shane Curran
Author-email: shane@curran.ie
Requires-Python: >=3.11,<3.13
Classifier: Programming Language :: Python :: 3
Classifier: Programming Language :: Python :: 3.11
Classifier: Programming Language :: Python :: 3.12
Requires-Dist: en-spacy-pii-fast (>=0.0.0,<0.0.1)
Requires-Dist: pandas (>=2.1.2,<3.0.0)
Requires-Dist: presidio-analyzer (>=2.2.350,<3.0.0)
